wavelinkcord/__init__.py
wavelinkcord/__main__.py
wavelinkcord/backoff.py
wavelinkcord/enums.py
wavelinkcord/exceptions.py
wavelinkcord/filters.py
wavelinkcord/node.py
wavelinkcord/payloads.py
wavelinkcord/player.py
wavelinkcord/queue.py
wavelinkcord/tracks.py
wavelinkcord/websocket.py
wavelinkcord/ext/spotify/__init__.py
wavelinkcord/ext/spotify/utils.py
wavelinkcord/types/events.py
wavelinkcord/types/request.py
wavelinkcord/types/state.py
wavelinkcord/types/track.py
wavelinkcord-2.6.6.dist-info/LICENSE
wavelinkcord-2.6.6.dist-info/METADATA
wavelinkcord-2.6.6.dist-info/WHEEL
wavelinkcord-2.6.6.dist-info/top_level.txt
wavelinkcord-2.6.6.dist-info/RECORD
