Metadata-Version: 2.1
Name: wavelinkcord
Version: 2.6.6
Summary: A robust and powerful Lavalink wrapper for nextcord
Author-email: Zyb3rWolfi <zyb3rwolfi@proton.me>
Project-URL: Homepage, https://github.com/PythonistaGuild/Wavelink
Classifier: License :: OSI Approved :: MIT License
Classifier: Intended Audience :: Developers
Classifier: Natural Language :: English
Classifier: Operating System :: OS Independent
Classifier: Programming Language :: Python :: 3.10
Classifier: Programming Language :: Python :: 3.11
Classifier: Topic :: Internet
Classifier: Topic :: Software Development :: Libraries
Classifier: Topic :: Software Development :: Libraries :: Python Modules
Classifier: Topic :: Utilities
Requires-Python: >=3.10
License-File: LICENSE
Requires-Dist: aiohttp <4,>=3.7.4
Requires-Dist: yarl ~=1.8.2
